.coveragerc
.gitignore
.pre-commit-config.yaml
.travis.yml
AUTHORS.rst
CHANGELOG.rst
LICENSE.txt
Makefile
README.rst
pyproject.toml
requirements.txt
setup.cfg
setup.py
tox.ini
docs/.buildinfo
docs/.nojekyll
docs/authors.html
docs/changelog.html
docs/commands.html
docs/genindex.html
docs/index.html
docs/license.html
docs/objects.inv
docs/py-modindex.html
docs/search.html
docs/searchindex.js
docs/_modules/index.html
docs/_modules/metapack_build/build.html
docs/_modules/metapack_build/cli/build.html
docs/_modules/metapack_build/cli/edit.html
docs/_modules/metapack_build/cli/new.html
docs/_modules/metapack_build/cli/s3.html
docs/_modules/metapack_build/cli/stats.html
docs/_modules/metapack_build/cli/update.html
docs/_modules/metapack_build/cli/url.html
docs/_modules/metapack_build/package/core.html
docs/_modules/metapack_build/package/csv.html
docs/_modules/metapack_build/package/excel.html
docs/_modules/metapack_build/package/filesystem.html
docs/_modules/metapack_build/package/s3.html
docs/_modules/metapack_build/package/zip.html
docs/_sources/authors.rst.txt
docs/_sources/changelog.rst.txt
docs/_sources/commands.rst.txt
docs/_sources/index.rst.txt
docs/_sources/license.rst.txt
docs/_sources/api/metapack_build.cli.rst.txt
docs/_sources/api/metapack_build.package.rst.txt
docs/_sources/api/metapack_build.rst.txt
docs/_sources/api/modules.rst.txt
docs/_sources/build/GeneratingRows.rst.txt
docs/_sources/build/Geographic.rst.txt
docs/_sources/build/GettingStarted.rst.txt
docs/_sources/build/Transforms.rst.txt
docs/_sources/build/WranglingPackages.rst.txt
docs/_static/alabaster.css
docs/_static/basic.css
docs/_static/custom.css
docs/_static/doctools.js
docs/_static/documentation_options.js
docs/_static/file.png
docs/_static/jquery-3.2.1.js
docs/_static/jquery.js
docs/_static/language_data.js
docs/_static/minus.png
docs/_static/plus.png
docs/_static/pygments.css
docs/_static/searchtools.js
docs/_static/underscore-1.3.1.js
docs/_static/underscore.js
src/metapack_build.egg-info/PKG-INFO
src/metapack_build.egg-info/SOURCES.txt
src/metapack_build.egg-info/dependency_links.txt
src/metapack_build.egg-info/entry_points.txt
src/metapack_build.egg-info/not-zip-safe
src/metapack_build.egg-info/requires.txt
src/metapack_build.egg-info/top_level.txt
