Metadata-Version: 2.1
Name: metapack-build
Version: 1.1.15
Summary: Metapack extension for building data packages
Home-page: https://github.com/Metatab/metatab-build
Author: Eric Busboom
Author-email: eric@civicknowledge.com
License: mit
Platform: any
Classifier: Development Status :: 4 - Beta
Classifier: Programming Language :: Python
Provides-Extra: testing
